bootstrap/__init__.py
bootstrap/__version__.py
bootstrap/compare.py
bootstrap/run.py
bootstrap/datasets/__init__.py
bootstrap/datasets/dataset.py
bootstrap/datasets/factory.py
bootstrap/datasets/transforms.py
bootstrap/datasets/utils.py
bootstrap/engines/__init__.py
bootstrap/engines/engine.py
bootstrap/engines/factory.py
bootstrap/engines/logger.py
bootstrap/lib/__init__.py
bootstrap/lib/logger.py
bootstrap/lib/options.py
bootstrap/lib/overwrite_print.py
bootstrap/lib/utils.py
bootstrap/models/__init__.py
bootstrap/models/factory.py
bootstrap/models/model.py
bootstrap/models/criterions/__init__.py
bootstrap/models/criterions/bce.py
bootstrap/models/criterions/cross_entropy.py
bootstrap/models/criterions/factory.py
bootstrap/models/criterions/nll.py
bootstrap/models/metrics/__init__.py
bootstrap/models/metrics/accuracy.py
bootstrap/models/metrics/factory.py
bootstrap/models/networks/__init__.py
bootstrap/models/networks/data_parallel.py
bootstrap/models/networks/factory.py
bootstrap/optimizers/__init__.py
bootstrap/optimizers/factory.py
bootstrap/optimizers/grad_clipper.py
bootstrap/optimizers/lr_scheduler.py
bootstrap/views/__init__.py
bootstrap/views/factory.py
bootstrap/views/generate.py
bootstrap/views/plotly.py
bootstrap/views/tensorboard.py
bootstrap/views/utils.py
bootstrap.pytorch-0.0.12.dist-info/DESCRIPTION.rst
bootstrap.pytorch-0.0.12.dist-info/METADATA
bootstrap.pytorch-0.0.12.dist-info/RECORD
bootstrap.pytorch-0.0.12.dist-info/WHEEL
bootstrap.pytorch-0.0.12.dist-info/metadata.json
bootstrap.pytorch-0.0.12.dist-info/top_level.txt
