Metadata-Version: 2.0
Name: bootstrap.pytorch
Version: 0.0.12
Summary: High level framework for starting Deep Learning projects
Home-page: https://github.com/cadene/bootstrap.pytorch
Author: Remi Cadene
Author-email: remi.cadene@icloud.com
License: UNKNOWN
Keywords: pytorch framework bootstrap deep learning scaffolding
Platform: UNKNOWN
Classifier: Development Status :: 3 - Alpha
Classifier: Intended Audience :: Developers
Classifier: Topic :: Software Development :: Build Tools
Classifier: License :: OSI Approved :: MIT License
Classifier: Programming Language :: Python :: 3.7
Requires-Dist: torch
Requires-Dist: numpy
Requires-Dist: argparse
Requires-Dist: pyyaml
Requires-Dist: plotly
Requires-Dist: seaborn
Requires-Dist: click
Requires-Dist: ipdb
Requires-Dist: tabulate
Requires-Dist: tensorboardX
